tahoma/__init__.py
tahoma/__version__.py
tahoma/get_devices_url.py
tahoma/tahoma.py
tahoma/icons/__init__.py
tahoma/icons/connected_house.png
tahoma/icons/water heater.png
tahoma/temp/__init__.py
tahoma/test/__init__.py
tahoma/test/test.py
tahoma-3.0.3.dist-info/LICENSE
tahoma-3.0.3.dist-info/METADATA
tahoma-3.0.3.dist-info/WHEEL
tahoma-3.0.3.dist-info/entry_points.txt
tahoma-3.0.3.dist-info/top_level.txt
tahoma-3.0.3.dist-info/RECORD
