Metadata-Version: 2.1
Name: tahoma
Version: 3.0.3
Summary: This is a very easy API for controlling Somfy Tahoma's devices written in Python3, thanks to the pyoverkiz API. You just need a three-word input to control a device
Author-email: Pzim-devdata <contact@pzim.fr>
Project-URL: Homepage, https://github.com/pzim-devdata/tahoma
Project-URL: Bug Tracker, https://github.com/pzim-devdata/tahoma/issues
Keywords: tahoma,somfy,api
Classifier: Programming Language :: Python :: 3
Classifier: License :: OSI Approved :: MIT License
Classifier: Operating System :: OS Independent
Requires-Python: >=3.7
License-File: LICENSE
Requires-Dist: pyoverkiz>=1.7.4
Requires-Dist: asyncio
Requires-Dist: argparse
Requires-Dist: future
Requires-Dist: requests
